MANIFEST.in
README.rst
setup.py
django_dbdev/__init__.py
django_dbdev/dbdev_backendregistry.py
django_dbdev/models.py
django_dbdev/version.json
django_dbdev.egg-info/PKG-INFO
django_dbdev.egg-info/SOURCES.txt
django_dbdev.egg-info/dependency_links.txt
django_dbdev.egg-info/not-zip-safe
django_dbdev.egg-info/pbr.json
django_dbdev.egg-info/requires.txt
django_dbdev.egg-info/top_level.txt
django_dbdev/backends/__init__.py
django_dbdev/backends/base.py
django_dbdev/backends/mysql.py
django_dbdev/backends/postgis.py
django_dbdev/backends/postgres.py
django_dbdev/backends/sqlite.py
django_dbdev/management/__init__.py
django_dbdev/management/commands/__init__.py
django_dbdev/management/commands/_base.py
django_dbdev/management/commands/dbdev_backup.py
django_dbdev/management/commands/dbdev_clearbackups.py
django_dbdev/management/commands/dbdev_createdump.py
django_dbdev/management/commands/dbdev_destroy.py
django_dbdev/management/commands/dbdev_fgrunserver.py
django_dbdev/management/commands/dbdev_guide.py
django_dbdev/management/commands/dbdev_init.py
django_dbdev/management/commands/dbdev_listbackups.py
django_dbdev/management/commands/dbdev_load_sqldump.py
django_dbdev/management/commands/dbdev_loaddump.py
django_dbdev/management/commands/dbdev_reinit.py
django_dbdev/management/commands/dbdev_restore.py
django_dbdev/management/commands/dbdev_serverinfo.py
django_dbdev/management/commands/dbdev_startserver.py
django_dbdev/management/commands/dbdev_stopserver.py
django_dbdev/templates/django_dbdev/mysqlbackend.rst
django_dbdev/templates/django_dbdev/postgresbackend.rst
django_dbdev/templates/django_dbdev/sqlitebackend.rst