Metadata-Version: 1.1
Name: django-dbdev
Version: 1.2.1
Summary: Makes it easy to create and manage databases during development.
Home-page: http://github.com/appressoas/django_dbdev
Author: Espen Angell Kristiansen
Author-email: post@espenak.net
License: BSD
Platform: UNKNOWN
Classifier: Development Status :: 4 - Beta
Classifier: Framework :: Django
Classifier: Intended Audience :: Developers
Classifier: License :: OSI Approved
Classifier: Operating System :: OS Independent
Classifier: Programming Language :: Python
